shpee/__init__.py
shpee/auth.py
shpee/client.py
shpee/shortlink.py
shpee-0.0.1.dist-info/LICENSE.md
shpee-0.0.1.dist-info/WHEEL
shpee-0.0.1.dist-info/METADATA
shpee-0.0.1.dist-info/RECORD
