Metadata-Version: 2.1
Name: shpee
Version: 0.0.1
Summary: Shopee Affiliate API Wrapper
License: MIT
Author: Ngalim Siregar
Author-email: ngalim.siregar@gmail.com
Requires-Python: >=3.8,<4.0
Classifier: License :: OSI Approved :: MIT License
Classifier: Programming Language :: Python :: 3
Classifier: Programming Language :: Python :: 3.8
Classifier: Programming Language :: Python :: 3.9
Requires-Dist: httpx (>=0.21.3,<0.22.0)
